MANIFEST.in
README.rst
setup.py
start_agent.sh
tox.ini
nfq/nfq-install-how-to.txt
nfq/NetfilterQueue-0.3.1-P2.7/CHANGES.txt
nfq/NetfilterQueue-0.3.1-P2.7/LICENSE.txt
nfq/NetfilterQueue-0.3.1-P2.7/PKG-INFO
nfq/NetfilterQueue-0.3.1-P2.7/README.rst
nfq/NetfilterQueue-0.3.1-P2.7/netfilterqueue.c
nfq/NetfilterQueue-0.3.1-P2.7/netfilterqueue.pxd
nfq/NetfilterQueue-0.3.1-P2.7/netfilterqueue.pyx
nfq/NetfilterQueue-0.3.1-P2.7/setup.py
nfq/NetfilterQueue-0.3.1-P3.3/CHANGES.txt
nfq/NetfilterQueue-0.3.1-P3.3/LICENSE.txt
nfq/NetfilterQueue-0.3.1-P3.3/MANIFEST.in
nfq/NetfilterQueue-0.3.1-P3.3/PKG-INFO
nfq/NetfilterQueue-0.3.1-P3.3/README.rst
nfq/NetfilterQueue-0.3.1-P3.3/netfilterqueue.c
nfq/NetfilterQueue-0.3.1-P3.3/netfilterqueue.pxd
nfq/NetfilterQueue-0.3.1-P3.3/netfilterqueue.pyx
nfq/NetfilterQueue-0.3.1-P3.3/setup.py
sfc/__init__.py
sfc/sfc_agent.py
sfc/sff_client.py
sfc.egg-info/PKG-INFO
sfc.egg-info/SOURCES.txt
sfc.egg-info/dependency_links.txt
sfc.egg-info/requires.txt
sfc.egg-info/top_level.txt
sfc/cli/__init__.py
sfc/cli/ovs_cli.py
sfc/cli/xe_cli.py
sfc/cli/xr_cli.py
sfc/common/__init__.py
sfc/common/classifier.py
sfc/common/launcher.py
sfc/common/services.py
sfc/common/sfc_globals.py
sfc/nsh/__init__.py
sfc/nsh/common.py
sfc/nsh/decode.py
sfc/nsh/encode.py
sfc/nsh/scapyNSH.py
sfc/nsh/service_index.py
test/conftest.py
test/classifier/test_classifier.py
test/classifier/data/acl-ipv4.json
test/classifier/data/acl-ipv6.json
test/classifier/data/acl-mac.json
test/classifier/data/acl-port.json
test/data/rendered_service_path_rpc.json
test/data/service_chains.json
test/data/service_classifier.json
test/data/service_function_forwarders.json
test/data/service_functions.json
test/data/service_path.json
test/services/test_services.py