Metadata-Version: 1.1
Name: sfc
Version: 0.1.357
Summary: Service Function Chaining
Home-page: https://wiki.opendaylight.org/view/Service_Function_Chaining:Main
Author: SFC Developers
Author-email: sfc-dev@lists.opendaylight.org
License: UNKNOWN
Keywords: sfc nsh nfq
Platform: UNKNOWN
Classifier: Development Status :: 3 - Alpha
Classifier: Intended Audience :: Developers
Classifier: Programming Language :: Python :: 3.4
Classifier: Operating System :: POSIX :: Linux
Classifier: Natural Language :: English
